jucell/__init__.py
jucell/template.html
jucell-0.1.5.dist-info/DESCRIPTION.rst
jucell-0.1.5.dist-info/METADATA
jucell-0.1.5.dist-info/RECORD
jucell-0.1.5.dist-info/WHEEL
jucell-0.1.5.dist-info/entry_points.txt
jucell-0.1.5.dist-info/metadata.json
jucell-0.1.5.dist-info/top_level.txt
