Metadata-Version: 2.0
Name: jucell
Version: 0.1.5
Summary: responsive jupyter iframe
Home-page: https://github.com/iseekwonderful/jupyter-iframe
Author: sheep
Author-email: sss3barry@gmail.com
License: MIT license
Keywords: jucell
Platform: UNKNOWN
Classifier: Development Status :: 2 - Pre-Alpha
Classifier: Intended Audience :: Developers
Classifier: License :: OSI Approved :: MIT License
Classifier: Natural Language :: English
Classifier: Programming Language :: Python :: 2
Classifier: Programming Language :: Python :: 2.6
Classifier: Programming Language :: Python :: 2.7
Classifier: Programming Language :: Python :: 3
Classifier: Programming Language :: Python :: 3.3
Classifier: Programming Language :: Python :: 3.4
Classifier: Programming Language :: Python :: 3.5
